ha_philipsjs-3.2.4.dist-info/licenses/LICENSE
haphilipsjs/__init__.py
haphilipsjs/__main__.py
haphilipsjs/auth.py
haphilipsjs/typing.py
haphilipsjs/data/__init__.py
haphilipsjs/data/v1.py
haphilipsjs/data/v6.py
haphilipsjs/dummy/__init__.py
haphilipsjs/dummy/v1.py
ha_philipsjs-3.2.4.dist-info/METADATA
ha_philipsjs-3.2.4.dist-info/WHEEL
ha_philipsjs-3.2.4.dist-info/top_level.txt
ha_philipsjs-3.2.4.dist-info/RECORD
