Metadata-Version: 2.4
Name: ha-philipsjs
Version: 3.2.4
Summary: jointSPACE API for Home-Assistant
Author-email: Daniel Perna <danielperna84@gmail.com>
License-Expression: MIT
Project-URL: Homepage, https://github.com/danielperna84/ha-philipsjs
Keywords: jointSPACE
Classifier: Intended Audience :: Developers
Classifier: Operating System :: OS Independent
Requires-Python: >=3.9
License-File: LICENSE
Requires-Dist: cryptography
Requires-Dist: httpx>=0.22.0
Provides-Extra: tests
Requires-Dist: pytest>3.6.4; extra == "tests"
Requires-Dist: pytest-cov<2.6; extra == "tests"
Requires-Dist: pytest-asyncio>=0.20.2; extra == "tests"
Requires-Dist: coveralls; extra == "tests"
Requires-Dist: pytest-mock; extra == "tests"
Requires-Dist: respx>=0.17.0; extra == "tests"
Dynamic: license-file
